llm_weights_mmap/__init__.py
llm_weights_mmap/loading.py
llm_weights_mmap/weights_separation.py
llm_weights_mmap-0.4.0.dist-info/METADATA
llm_weights_mmap-0.4.0.dist-info/WHEEL
llm_weights_mmap-0.4.0.dist-info/top_level.txt
llm_weights_mmap-0.4.0.dist-info/RECORD
