Metadata-Version: 2.1
Name: llm-weights-mmap
Version: 0.4.0
Summary: Microlib for memory-mapping LLM (large language models) weights
Author-email: Hristo Vrigazov <hvrigazov@gmail.com>
Project-URL: Homepage, https://github.com/microlib-org/llm_microlibs/llm_weights_mmap
Classifier: License :: OSI Approved :: MIT License
Classifier: Programming Language :: Python
Classifier: Programming Language :: Python :: 3
Requires-Python: >=3.8
Requires-Dist: torch
Requires-Dist: numpy
Provides-Extra: dev
Requires-Dist: pytest ; extra == 'dev'
Requires-Dist: tqdm ; extra == 'dev'
